{
    "configurations": [
        {
            "name": "Linux",
            "includePath": [
                "${workspaceFolder}/include/**",
                "${workspaceFolder}/src/**"
            ],
            "browse": {
                "path": [
                    "${workspaceFolder}/include",
                    "${workspaceFolder}/src"
                ],
                "limitSymbolsToIncludedHeaders": false
            },
            "compilerPath": "/usr/bin/g++",
            "cStandard": "c17",
            "cppStandard": "c++17",
            "compileCommands": "${workspaceFolder}/build/compile_commands.json",
            "intelliSenseMode": "linux-gcc-x64",
            "configurationProvider": "ms-vscode.cmake-tools",
            "defines": [
                "DEBUG_MCAC",
                "WITH_HDF5"
            ]
        }
    ],
    "version": 4
}